fused/__init__.py
fused/_auth.py
fused/_environment.py
fused/_global_api.py
fused/_lite.py
fused/_load_udf.py
fused/_optional_deps.py
fused/_options.py
fused/_public_api.py
fused/_request.py
fused/_run.py
fused/_secrets.py
fused/_str_utils.py
fused/_submit.py
fused/_utils.py
fused/_version.py
fused/context.py
fused/types.py
fused/warnings.py
fused/_fasttortoise/__init__.py
fused/_fasttortoise/_api.py
fused/_formatter/common.py
fused/_formatter/formatter_eval_result.py
fused/_formatter/formatter_job_config.py
fused/_formatter/formatter_jobs.py
fused/_formatter/formatter_options.py
fused/_formatter/formatter_udf_access_token.py
fused/_formatter/noraise.py
fused/_formatter/udf.py
fused/_h3/__init__.py
fused/_h3/index.py
fused/_h3/ingest.py
fused/_h3/read.py
fused/_quick/__init__.py
fused/_quick/udf.py
fused/_static/__init__.py
fused/_static/css/__init__.py
fused/_static/css/style.css
fused/_static/html/__init__.py
fused/_static/html/icons-svg-inline.html
fused/_udf/__init__.py
fused/_udf/_line_profiler_vendored.py
fused/_udf/args.py
fused/_udf/compile_v2.py
fused/_udf/decorators.py
fused/_udf/execute_v2.py
fused/_udf/noop_decorators.py
fused/_udf/state.py
fused/api/__init__.py
fused/api/_fd_filesystem.py
fused/api/_public_api.py
fused/api/api.py
fused/api/credentials.py
fused/api/docker_api.py
fused/core/__init__.py
fused/core/_cache.py
fused/core/_context.py
fused/core/_download.py
fused/core/_fs_utils.py
fused/core/_realtime_ops.py
fused/core/_serialization.py
fused/core/_table_ops.py
fused/core/_udf_ops.py
fused/ipython/fused_magics.py
fused/models/__init__.py
fused/models/_inplace.py
fused/models/base.py
fused/models/request.py
fused/models/schema.py
fused/models/urls.py
fused/models/_codegen/__init__.py
fused/models/_codegen/job.py
fused/models/_codegen/udf.py
fused/models/api/__init__.py
fused/models/api/_cronjob.py
fused/models/api/_list.py
fused/models/api/dataset.py
fused/models/api/job.py
fused/models/api/udf_access_token.py
fused/models/internal/__init__.py
fused-1.29.0.dist-info/METADATA
fused-1.29.0.dist-info/WHEEL
fused-1.29.0.dist-info/RECORD
